PartyDownloader/PartyDownloader.py
PartyDownloader/__init__.py
party_downloader-0.0.8.dist-info/METADATA
party_downloader-0.0.8.dist-info/WHEEL
party_downloader-0.0.8.dist-info/top_level.txt
party_downloader-0.0.8.dist-info/RECORD
