Metadata-Version: 2.1
Name: party-downloader
Version: 0.0.8
Summary: Simple tool to download files from coomer.party
Requires-Dist: requests
Requires-Dist: tqdm
Requires-Dist: beautifulsoup4
